[
  {
    "name": "Job",
    "path": "/Job",
    "component": "C:\\\\Users\\\\SeifRashad\\\\Desktop\\\\test\\\\eco-loan\\\\pages\\\\Job.vue",
    "chunkName": "pages/Job",
    "_name": "_672c2cfa"
  },
  {
    "name": "Plan",
    "path": "/Plan",
    "component": "C:\\\\Users\\\\SeifRashad\\\\Desktop\\\\test\\\\eco-loan\\\\pages\\\\Plan.vue",
    "chunkName": "pages/Plan",
    "_name": "_509e20bc"
  },
  {
    "name": "index",
    "path": "/",
    "component": "C:\\\\Users\\\\SeifRashad\\\\Desktop\\\\test\\\\eco-loan\\\\pages\\\\index.vue",
    "chunkName": "pages/index",
    "_name": "_be3f5b22"
  }
]
